main_stream/__about__.py
main_stream/__init__.py
main_stream-0.1.0.dist-info/METADATA
main_stream-0.1.0.dist-info/WHEEL
main_stream-0.1.0.dist-info/top_level.txt
main_stream-0.1.0.dist-info/RECORD
